camtrapml/__init__.py
camtrapml/dataset.py
camtrapml/detection/__init__.py
camtrapml/detection/models/__init__.py
camtrapml/detection/models/megadetector.py
camtrapml/detection/models/tensorflow.py
camtrapml/detection/utils.py
camtrapml/download.py
camtrapml/image/__init__.py
camtrapml/image/exif.py
camtrapml/image/utils.py
camtrapml-0.4.1.dist-info/LICENSE.md
camtrapml-0.4.1.dist-info/WHEEL
camtrapml-0.4.1.dist-info/METADATA
camtrapml-0.4.1.dist-info/RECORD
