Metadata-Version: 2.1
Name: camtrapml
Version: 0.4.1
Summary: CamTrapML is a Python library for Detecting, Classifying, and Analysing Wildlife Camera Trap Imagery.
Home-page: https://github.com/bencevans/camtrapml
License: MIT
Keywords: wildlife,camtrap,camera,trap,imagery,classification,detection,analysis,conservation
Author: Benjamin C. Evans
Author-email: Benjamin.Evans@brunel.ac.uk
Requires-Python: >=3.8,<3.11
Classifier: Intended Audience :: Developers
Classifier: Intended Audience :: Science/Research
Classifier: License :: OSI Approved :: MIT License
Classifier: Programming Language :: Python :: 3
Classifier: Programming Language :: Python :: 3.8
Classifier: Programming Language :: Python :: 3.9
Classifier: Programming Language :: Python :: 3.10
Classifier: Programming Language :: Python :: 3
Classifier: Programming Language :: Python :: 3.6
Classifier: Programming Language :: Python :: 3.7
Classifier: Programming Language :: Python :: 3.8
Classifier: Topic :: Scientific/Engineering :: Artificial Intelligence
Classifier: Topic :: Scientific/Engineering :: Bio-Informatics
Classifier: Topic :: Scientific/Engineering :: Image Processing
Classifier: Topic :: Scientific/Engineering :: Image Recognition
Classifier: Topic :: Scientific/Engineering :: Information Analysis
Classifier: Topic :: Scientific/Engineering :: Visualization
Requires-Dist: Pillow (>=9,<10)
Requires-Dist: PyExifTool (>=0.4.13,<0.5.0)
Requires-Dist: font-fredoka-one (>=0.0.4,<0.0.5)
Requires-Dist: h5py (>=3.7.0,<4.0.0)
Requires-Dist: matplotlib (>=3,<4)
Requires-Dist: numpy (>=1,<2)
Requires-Dist: requests (>=2,<3)
Requires-Dist: scikit-learn (==1.0.1)
Requires-Dist: scipy (>=1.9.1,<2.0.0)
Requires-Dist: tensorflow (>=2.10.0,<3.0.0)
Requires-Dist: tensorflow-hub (>=0.12.0,<0.13.0)
Requires-Dist: tqdm (>=4,<5)
Project-URL: Bug Tracker, https://github.com/bencevans/camtrapml/issues
Project-URL: Documentation, https://github.com/bencevans/camtrapml
Project-URL: Repository, https://github.com/bencevans/camtrapml
